dashvis/DashNetwork.py
dashvis/__init__.py
dashvis/_imports_.py
dashvis/dashvis.min.js
dashvis/dashvis.min.js.map
dashvis/metadata.json
dashvis/package-info.json
dashvis/stylesheets.py
dashvis-0.1.14.dist-info/LICENSE
dashvis-0.1.14.dist-info/LICENSE-APACHE-2.0
dashvis-0.1.14.dist-info/METADATA
dashvis-0.1.14.dist-info/WHEEL
dashvis-0.1.14.dist-info/top_level.txt
dashvis-0.1.14.dist-info/RECORD
