Metadata-Version: 2.1
Name: dashvis
Version: 0.1.14
Summary: Dash Plotly implementation of vis.js library
Home-page: https://github.com/lewkoo/dashvis
Author: Levko Ivanchuk
Author-email: lewkoo@gmail.com
License: MIT, Apache-2.0
Project-URL: Documentation, https://github.com/lewkoo/dashvis/wiki
Project-URL: Bug Reports, https://github.com/lewkoo/dashvis/issues
Project-URL: Source Code, https://github.com/lewkoo/dashvis
Project-URL: Discussions, https://github.com/lewkoo/dashvis/discussions
Project-URL: Pull Requests, https://github.com/lewkoo/dashvis/pulls
Classifier: Development Status :: 1 - Planning
Classifier: Environment :: Web Environment
Classifier: Framework :: Dash
Classifier: Intended Audience :: Developers
Classifier: License :: OSI Approved :: Apache Software License
Classifier: License :: OSI Approved :: MIT License
Classifier: Topic :: Software Development :: Build Tools
Classifier: Programming Language :: Python :: 3.8
Classifier: Programming Language :: Python :: 3.9
Classifier: Programming Language :: Python :: 3.10
Classifier: Programming Language :: Python :: 3 :: Only
Classifier: Operating System :: OS Independent
Requires-Python: >=3.8
License-File: LICENSE
License-File: LICENSE-APACHE-2.0
